{
  "variants": {
    "facing=up": {
      "model": "catwalksinc:block/cage_lamp"
     },
     "facing=down": {
      "model": "catwalksinc:block/cage_lamp",
      "x": 180
    },
    "facing=north": {
      "model": "catwalksinc:block/cage_lamp",
      "x": 90
    },
    "facing=south": {
      "model": "catwalksinc:block/cage_lamp",
      "x": 90, "y": 180
    },
    "facing=west": {
      "model": "catwalksinc:block/cage_lamp",
      "x": 90, "y": 270 
    },
    "facing=east": {
      "model": "catwalksinc:block/cage_lamp",
      "x": 90, "y": 90
    }
  }
}